xml_fmt/__init__.py
xml_fmt/__main__.py
xml_fmt/py.typed
xml_fmt-1.0.1.dist-info/METADATA
xml_fmt-1.0.1.dist-info/WHEEL
xml_fmt-1.0.1.dist-info/entry_points.txt
xml_fmt-1.0.1.dist-info/licenses/LICENSE.txt
xml_fmt-1.0.1.dist-info/RECORD
