Metadata-Version: 2.4
Name: xml-fmt
Version: 1.0.1
Summary: Run pre-commit with uv
Project-URL: Bug Tracker, https://github.com/tox-dev/xml-fmt/issues
Project-URL: Changelog, https://github.com/tox-dev/xml-fmt/releases
Project-URL: Documentation, https://github.com/tox-dev/xml-fmt/
Project-URL: Source Code, https://github.com/tox-dev/xml-fmt
Author-email: Bernat Gabor <gaborjbernat@gmail.com>
License: Permission is hereby granted, free of charge, to any person obtaining a
License-File: LICENSE.txt
Keywords: XML,format
Classifier: License :: OSI Approved :: MIT License
Classifier: Operating System :: OS Independent
Classifier: Programming Language :: Python
Classifier: Programming Language :: Python :: 3 :: Only
Classifier: Programming Language :: Python :: 3.9
Classifier: Programming Language :: Python :: 3.10
Classifier: Programming Language :: Python :: 3.11
Classifier: Programming Language :: Python :: 3.12
Classifier: Programming Language :: Python :: 3.13
Requires-Python: >=3.9
